build/lib/build/lib/example/__init__.py
build/lib/build/lib/example/auth_middleware.py
build/lib/build/lib/example/ctxvars.py
build/lib/build/lib/example/curd.py
build/lib/build/lib/example/curd_cbv.py
build/lib/build/lib/example/err_handle.py
build/lib/build/lib/example/include_api.py
build/lib/build/lib/example/json_rpc_client.py
build/lib/build/lib/example/json_rpc_server.py
build/lib/build/lib/example/rate_limiter.py
build/lib/build/lib/example/redis_demo.py
build/lib/build/lib/example/req_hook.py
build/lib/build/lib/example/sentry_demo.py
build/lib/build/lib/example/sqlalchemy_db.py
build/lib/build/lib/example/use_simple_api_docs.py
build/lib/build/lib/simple_starlette/__init__.py
build/lib/build/lib/simple_starlette/app.py
build/lib/build/lib/simple_starlette/args.py
build/lib/build/lib/simple_starlette/code.py
build/lib/build/lib/simple_starlette/config.py
build/lib/build/lib/simple_starlette/ctx.py
build/lib/build/lib/simple_starlette/dispatch_request.py
build/lib/build/lib/simple_starlette/exceptions.py
build/lib/build/lib/simple_starlette/include.py
build/lib/build/lib/simple_starlette/logger.py
build/lib/build/lib/simple_starlette/responses.py
build/lib/build/lib/simple_starlette/route.py
build/lib/build/lib/simple_starlette/types.py
build/lib/build/lib/simple_starlette/cache/__init__.py
build/lib/build/lib/simple_starlette/cache/guava_cache.py
build/lib/build/lib/simple_starlette/cache/memory_cache.py
build/lib/build/lib/simple_starlette/cache/redis_cache.py
build/lib/build/lib/simple_starlette/db/__init__.py
build/lib/build/lib/simple_starlette/db/db_sqlalchemy.py
build/lib/build/lib/simple_starlette/db/redis.py
build/lib/build/lib/simple_starlette/db/sqlalchemy_types.py
build/lib/build/lib/simple_starlette/docs/__init__.py
build/lib/build/lib/simple_starlette/docs/api.py
build/lib/build/lib/simple_starlette/docs/react_static/__init__.py
build/lib/build/lib/simple_starlette/http_client/__init__.py
simple_starlette-3.1.0.dist-info/LICENSE
simple_starlette-3.1.0.dist-info/METADATA
simple_starlette-3.1.0.dist-info/WHEEL
simple_starlette-3.1.0.dist-info/top_level.txt
simple_starlette-3.1.0.dist-info/RECORD
