Metadata-Version: 2.1
Name: simple-starlette
Version: 3.1.0
Summary: a micro server
Author: asbt
Author-email: sg5htd@gmail.com
License-File: LICENSE
Requires-Dist: black ==22.3.0
Requires-Dist: pytest ==7.1.1
Requires-Dist: SQLAlchemy ==1.4.27
Requires-Dist: asyncmy ==0.2.5
Requires-Dist: aiomysql ==0.0.21
Requires-Dist: starlette ==0.16.0
Requires-Dist: pydantic ==1.8.2
Requires-Dist: werkzeug ==2.0.2
Requires-Dist: uvicorn[standard] ==0.15.0
Requires-Dist: jsonrpcclient ==4.0.1
Requires-Dist: jsonrpcserver ==5.0.4
Requires-Dist: requests ==2.25.1
Requires-Dist: pyjwt ==2.4.0
Requires-Dist: sentry-sdk ==0.10.2
Requires-Dist: redis ==4.4.0
